cogwheel/__init__.py
cogwheel/_version.py
cogwheel/cosmology.py
cogwheel/data.py
cogwheel/gw_plotting.py
cogwheel/gw_utils.py
cogwheel/plotting.py
cogwheel/pn_coordinates.py
cogwheel/posterior.py
cogwheel/postprocessing.py
cogwheel/prior.py
cogwheel/prior_ratio.py
cogwheel/sampling.py
cogwheel/skyloc_angles.py
cogwheel/utils.py
cogwheel/waveform.py
cogwheel/data/events_metadata.csv
cogwheel/data/example_asds/asd_H_O3.npy
cogwheel/data/example_asds/asd_H_O4.npy
cogwheel/data/example_asds/asd_L_O3.npy
cogwheel/data/example_asds/asd_L_O4.npy
cogwheel/data/example_asds/asd_V_O3.npy
cogwheel/gw_prior/__init__.py
cogwheel/gw_prior/combined.py
cogwheel/gw_prior/extrinsic.py
cogwheel/gw_prior/mass.py
cogwheel/gw_prior/miscellaneous.py
cogwheel/gw_prior/pn.py
cogwheel/gw_prior/spin.py
cogwheel/gw_prior/tides.py
cogwheel/gw_prior/twosquircle.py
cogwheel/likelihood/__init__.py
cogwheel/likelihood/lensing_type_ii.py
cogwheel/likelihood/likelihood.py
cogwheel/likelihood/marginalized_distance.py
cogwheel/likelihood/marginalized_distance_phase.py
cogwheel/likelihood/marginalized_extrinsic.py
cogwheel/likelihood/marginalized_extrinsic_qas.py
cogwheel/likelihood/reference_waveform_finder.py
cogwheel/likelihood/relative_binning.py
cogwheel/likelihood/marginalization/__init__.py
cogwheel/likelihood/marginalization/base.py
cogwheel/likelihood/marginalization/coherent_score_hm.py
cogwheel/likelihood/marginalization/coherent_score_qas.py
cogwheel/likelihood/marginalization/lookup_table.py
cogwheel/likelihood/marginalization/skydict.py
cogwheel/tests/__init__.py
cogwheel/tests/test_gw_prior.py
cogwheel/tests/test_gw_utils.py
cogwheel/tests/test_plotting.py
cogwheel/tests/test_posterior.py
cogwheel/tests/test_skyloc_angles.py
cogwheel/tests/test_waveform.py
cogwheel/validation/1-generate_injections.ipynb
cogwheel/validation/2-inference.ipynb
cogwheel/validation/__init__.py
cogwheel/validation/analyze.py
cogwheel/validation/generate_injections.py
cogwheel/validation/inference.py
cogwheel_pe-1.5.0.dist-info/METADATA
cogwheel_pe-1.5.0.dist-info/WHEEL
cogwheel_pe-1.5.0.dist-info/top_level.txt
cogwheel_pe-1.5.0.dist-info/RECORD
