Metadata-Version: 2.4
Name: cogwheel-pe
Version: 1.5.0
Summary: Parameter estimation of gravitational wave sources
Author: Javier Roulet, Tejaswi Venumadhav, Jonathan Mushkin, Tousif Islam, Seth Olsen, Jay Wadekar
Maintainer-email: Javier Roulet <jroulet@uchicago.edu>
Project-URL: Source, https://github.com/jroulet/cogwheel
Classifier: License :: OSI Approved :: GNU General Public License (GPL)
Classifier: Programming Language :: Python :: 3.9
Classifier: Programming Language :: Python :: 3.10
Classifier: Programming Language :: Python :: 3.11
Classifier: Programming Language :: Python :: 3.12
Classifier: Programming Language :: Python :: 3.13
Classifier: Programming Language :: Python :: 3.14
Requires-Python: >=3.9
Requires-Dist: ipykernel
Requires-Dist: ipympl
Requires-Dist: ipywidgets
Requires-Dist: lalsuite
Requires-Dist: matplotlib
Requires-Dist: notebook
Requires-Dist: numba
Requires-Dist: pandas>=2.0
Requires-Dist: pyarrow
Requires-Dist: scipy
Requires-Dist: setuptools_scm
Requires-Dist: gwpy
Requires-Dist: dynesty
Requires-Dist: nautilus-sampler
Requires-Dist: zeus-mcmc
Provides-Extra: dev
Requires-Dist: build; extra == "dev"
Requires-Dist: grayskull; extra == "dev"
Provides-Extra: full
Requires-Dist: pymultinest; extra == "full"
